kinez
