Metadata-Version: 2.1
Name: kinez
Version: 0.0.4
Summary: Fun
Home-page: UNKNOWN
Author: Kinez
Author-email: vodrabro@gmail.com
License: UNKNOWN
Keywords: python
Platform: UNKNOWN
Classifier: Development Status :: 1 - Planning
Classifier: Intended Audience :: Developers
Classifier: Programming Language :: Python :: 3
Classifier: Operating System :: Unix
Classifier: Operating System :: MacOS :: MacOS X
Classifier: Operating System :: Microsoft :: Windows
License-File: LICENSE
